{
    "thunderstorm with light rain": "thunderstorm",
    "thunderstorm with rain": "thunderstorm",
    "thunderstorm with heavy rain": "thunderstorm",
    "light thunderstorm": "thunderstorm",
    "thunderstorm": "thunderstorm",
    "heavy thunderstorm": "thunderstorm",
    "ragged thunderstorm": "thunderstorm",
    "thunderstorm with light drizzle": "thunderstorm",
    "thunderstorm with drizzle": "thunderstorm",
    "thunderstorm with heavy drizzle": "thunderstorm",
    "light intensity drizzle": "showerrain",
    "drizzle": "showerrain",
    "heavy intensity drizzle": "showerrain",
    "light intensity drizzle rain": "showerrain",
    "drizzle rain": "showerrain",
    "heavy intensity drizzle rain": "showerrain",
    "shower rain and drizzle": "showerrain",
    "heavy shower rain and drizzle": "showerrain",
    "shower drizzle": "showerrain",
    "light rain": "rain",
    "moderate rain": "rain",
    "heavy intensity rain": "rain",
    "very heavy rain": "rain",
    "extreme rain": "rain",
    "freezing rain": "snow",
    "light intensity shower rain": "showerrain",
    "shower rain": "showerrain",
    "heavy intensity shower rain": "showerrain",
    "ragged shower rain": "showerrain",
    "light snow": "snow",
    "Snow": "snow",
    "Heavy snow": "snow",
    "Sleet": "snow",
    "Light shower sleet": "snow",
    "Shower sleet": "snow",
    "Light rain and snow": "snow",
    "Rain and snow": "snow",
    "Light shower snow": "snow",
    "Shower snow": "snow",
    "Heavy shower snow": "snow",
    "mist": "mist",
    "Smoke": "mist",
    "Haze": "mist",
    "sand/ dust whirls": "mist",
    "fog": "mist",
    "sand": "mist",
    "dust": "mist",
    "volcanic ash": "mist",
    "squalls": "mist",
    "tornado": "mist",
    "clear sky": "sun",
    "few clouds": "fewclouds",
    "scattered clouds": "scatteredclouds",
    "broken clouds": "brokenclouds",
    "overcast clouds": "brokenclouds"

}